{"AmmarAr":{"email":"johndoe@example.com","username":"AmmarAr","password":"password123","logins":1,"lastLogin":"2024-12-10 23:42","firstName":"Ammar","lastName":"Ammmm"},"Alaaaa":{"email":"johndoe@example.com","username":"Alaaaa","password":"password123","logins":1,"lastLogin":"2024-12-10 23:42","firstName":"Alaa","lastName":"Alawn"},"JohnDoe":{"email":"johndoe@example.com","username":"JohnDoe","password":"password123","logins":0,"lastLogin":"","firstName":"John","lastName":"Doe"},"John6565Doe":{"email":"johndoe@example.com","username":"John6565Doe","password":"password123","logins":0,"lastLogin":"","firstName":"John29","lastName":"Doe"},"MuathHassoun":{"email":"johndoe@example.com","username":"MuathHassoun","password":"password123","logins":1,"lastLogin":"2024-12-10 23:41","firstName":"Muath","lastName":"Hassoun"},"Activate":{"email":"johndoe@example.com","username":"Activate","password":"password123","logins":0,"lastLogin":"","firstName":"JohnAct","lastName":"Doe"}}